thaixtransformers/__init__.py
thaixtransformers/core.py
thaixtransformers/preprocess.py
thaixtransformers/roberta.py
thaixtransformers-0.1.0.dist-info/LICENSE
thaixtransformers-0.1.0.dist-info/METADATA
thaixtransformers-0.1.0.dist-info/WHEEL
thaixtransformers-0.1.0.dist-info/top_level.txt
thaixtransformers-0.1.0.dist-info/RECORD
