Metadata-Version: 2.1
Name: thaixtransformers
Version: 0.1.0
Summary: ThaiXtransformers: Use Pretraining RoBERTa based Thai language models from VISTEC-depa AI Research Institute of Thailand.
Home-page: https://github.com/pythainlp/thaixtransformers
Author: PyThaiNLP
Author-email: 
License: Apache Software License 2.0
Project-URL: Documentation, https://github.com/pythainlp/thaixtransformers
Project-URL: Source Code, https://github.com/pythainlp/thaixtransformers
Project-URL: Bug Tracker, https://github.com/pythainlp/thaixtransformers/issues
Keywords: thainlp,NLP,natural language processing,text analytics,text processing,localization,computational linguistics,ThaiNLP,Thai NLP,Thai language
Classifier: Development Status :: 3 - Alpha
Classifier: Programming Language :: Python :: 3
Classifier: Intended Audience :: Developers
Classifier: License :: OSI Approved :: Apache Software License
Classifier: Natural Language :: Thai
Classifier: Topic :: Scientific/Engineering :: Artificial Intelligence
Classifier: Topic :: Text Processing
Classifier: Topic :: Text Processing :: General
Classifier: Topic :: Text Processing :: Linguistic
Requires-Python: >=3.8
License-File: LICENSE
Requires-Dist: transformers (>=4.6)
Requires-Dist: sentencepiece
Requires-Dist: emoji
Requires-Dist: pythainlp (>=2.2.4)
Requires-Dist: tokenizers
